tgusers/__init__.py
tgusers/bot/bot_class.py
tgusers/class_models/table.py
tgusers/database/database.py
tgusers/dataclasses/rooms.py
tgusers/errors/rooms.py
tgusers/rooms/container.py
tgusers/rooms/room_class.py
tgusers/tables/messages.py
tgusers/tables/tables.py
tgusers/tables/users.py
tgusers/utils/runfunc.py
tgusers/utils/validator.py
tgusers-0.0.14.data/data/LICENSE
tgusers-0.0.14.data/data/README.md
tgusers-0.0.14.dist-info/LICENSE
tgusers-0.0.14.dist-info/METADATA
tgusers-0.0.14.dist-info/WHEEL
tgusers-0.0.14.dist-info/top_level.txt
tgusers-0.0.14.dist-info/RECORD
