Metadata-Version: 2.1
Name: tgusers
Version: 0.0.14
Summary: Mini framework for creating bots with tracking the user's position in the so-called "rooms". Based on aiogram.
Home-page: https://github.com/drogi17/TgUsers
Author: ic_it
Author-email: 
License: GNU 3
Platform: UNKNOWN
Classifier: Operating System :: OS Independent
Classifier: Intended Audience :: Developers
Classifier: Programming Language :: Python :: 3
Requires-Python: >=3.6
Requires-Dist: aiogram (==2.9.2)
Requires-Dist: psycopg2 (==2.8.5)
